pykinisi/KinisiCommands.py
pykinisi/KinisiController.py
pykinisi/__init__.py
pykinisi-1.0.4.1.dist-info/LICENSE
pykinisi-1.0.4.1.dist-info/METADATA
pykinisi-1.0.4.1.dist-info/WHEEL
pykinisi-1.0.4.1.dist-info/top_level.txt
pykinisi-1.0.4.1.dist-info/RECORD
